{
  "students": [
    {
      "student": "Kalle Kustaa",
      "course": "Fullstack",
      "id": 1
    },
    {
      "student": "Maija Meik채l채inen",
      "course": "Ohtu",
      "id": 2
    },
    {
      "student": "Jaska Jokunen",
      "course": "K채j채",
      "id": 3
    },
    {
      "student": "Nakke Nakuttaja",
      "course": "OHTU",
      "id": 4
    },
    {
      "student": "uushakija",
      "course": "OHTU",
      "id": 5
    },
    {
      "student": "testt",
      "course": "test",
      "id": 6
    },
    {
      "student": {
        "id": "111",
        "last_name": "bisi",
        "first_names": "olli",
        "nickname": "sibbe",
        "phone_number": "1234",
        "email": "olc"
      },
      "id": 7
    },
    {
      "student": {
        "id": "111",
        "last_name": "svala",
        "first_names": "viku",
        "nickname": "viku",
        "phone_number": "11",
        "email": ""
      },
      "id": 8
    },
    {
      "student": {
        "id": "a",
        "last_name": "a",
        "first_names": "a",
        "nickname": "a",
        "phone_number": "a",
        "email": "a"
      },
      "id": 9
    },
    {
      "student": {
        "id": "",
        "last_name": "",
        "first_names": "",
        "nickname": "",
        "phone_number": "",
        "email": ""
      },
      "id": 10
    },
    {
      "student": {
        "id": "",
        "last_name": "",
        "first_names": "",
        "nickname": "",
        "phone_number": "",
        "email": ""
      },
      "id": 11
    }
  ]
}